api/__init__.py
api/apps.py
api/models.py
api/preexisting_models.py
api/serializers.py
api/urls.py
api/views.py
api/migrations/__init__.py
hackoregon_sandbox-1.64.dist-info/METADATA
hackoregon_sandbox-1.64.dist-info/WHEEL
hackoregon_sandbox-1.64.dist-info/top_level.txt
hackoregon_sandbox-1.64.dist-info/RECORD
